xcfsyslogger
