Metadata-Version: 1.0
Name: xcfsyslogger
Version: 1.0.1
Summary: this is a test package for packing python liberaries tutorial.
Home-page: http://blog.useasp.net/
Author: liuweibo
Author-email: liuweibo@xiachufang.com
License: MIT
Keywords: xiachufang
Platform: UNKNOWN
